deplpy/__init__.py
deplpy/bayes/__init__.py
deplpy/sim/__init__.py
deplpy-0.1.0.dist-info/licenses/LICENSE
deplpy-0.1.0.dist-info/METADATA
deplpy-0.1.0.dist-info/WHEEL
deplpy-0.1.0.dist-info/top_level.txt
deplpy-0.1.0.dist-info/RECORD
