Metadata-Version: 2.4
Name: deplpy
Version: 0.1.0
Summary: Bayesian depletion-model inference & simulation for fish-population dynamics
Author-email: Abdelouahed Ben Mhamed <a.benmhamed@intelligentica.net>
Classifier: Programming Language :: Python :: 3
Classifier: License :: OSI Approved :: MIT License
Classifier: Operating System :: OS Independent
Requires-Python: >=3.8
License-File: LICENSE
Requires-Dist: numpy
Requires-Dist: scipy
Requires-Dist: pandas
Requires-Dist: pymc3
Dynamic: license-file
